xarrayutils/__init__.py
xarrayutils/_version.py
xarrayutils/build_grids.py
xarrayutils/climate_indicies.py
xarrayutils/file_handling.py
xarrayutils/filtering.py
xarrayutils/plotting.py
xarrayutils/utilities.py
xarrayutils/utils.py
xarrayutils/xgcm_utils.py
xarrayutils/xmitgcm_utils.py
xarrayutils/test/__init__.py
xarrayutils/test/datasets.py
xarrayutils/test/test_build_grids.py
xarrayutils/test/test_file_handling.py
xarrayutils/test/test_filtering.py
xarrayutils/test/test_plotting.py
xarrayutils/test/test_utils.py
xarrayutils/test/test_xgcm_utils.py
xarrayutils/test/test_xmitgcm_utils.py
xarrayutils-2.0.1.dist-info/LICENSE
xarrayutils-2.0.1.dist-info/METADATA
xarrayutils-2.0.1.dist-info/WHEEL
xarrayutils-2.0.1.dist-info/top_level.txt
xarrayutils-2.0.1.dist-info/RECORD
