Metadata-Version: 2.1
Name: xarrayutils
Version: 2.0.1
Summary: A collection of various tools for data analysis built on top of xarray and xgcm
Home-page: https://github.com/jbusecke/xarrayutils
Author: xarrayutils Developers
Author-email: julius@ldeo.columbia.edu
License: MIT
Platform: UNKNOWN
Classifier: Development Status :: 4 - Beta
Classifier: Intended Audience :: Science/Research
Classifier: Topic :: Scientific/Engineering
Classifier: License :: OSI Approved :: MIT License
Classifier: Operating System :: OS Independent
Classifier: Programming Language :: Python :: 3.9
Classifier: Programming Language :: Python :: 3.10
Requires-Python: >=3.9
License-File: LICENSE
Requires-Dist: xarray >=0.14.1
Requires-Dist: dask
Requires-Dist: numpy
Requires-Dist: scipy
Provides-Extra: complete
Requires-Dist: xarray >=0.14.1 ; extra == 'complete'
Requires-Dist: dask ; extra == 'complete'
Requires-Dist: numpy ; extra == 'complete'
Requires-Dist: scipy ; extra == 'complete'
Provides-Extra: dev
Requires-Dist: xarray >=0.14.1 ; extra == 'dev'
Requires-Dist: dask ; extra == 'dev'
Requires-Dist: numpy ; extra == 'dev'
Requires-Dist: scipy ; extra == 'dev'
Requires-Dist: pytest ; extra == 'dev'
Requires-Dist: pytest-cov ; extra == 'dev'
Requires-Dist: flake8 ; extra == 'dev'
Requires-Dist: black ; extra == 'dev'
Requires-Dist: codecov ; extra == 'dev'
Provides-Extra: docs
Requires-Dist: sphinx ; extra == 'docs'
Requires-Dist: sphinxcontrib-srclinks ; extra == 'docs'
Requires-Dist: sphinx-pangeo-theme ; extra == 'docs'
Requires-Dist: numpydoc ; extra == 'docs'
Requires-Dist: IPython ; extra == 'docs'
Requires-Dist: nbsphinx ; extra == 'docs'
